{
  "collectionName": "components_motel_infos",
  "info": {
    "name": "info",
    "icon": "info-circle"
  },
  "options": {},
  "attributes": {
    "title": {
      "type": "string"
    },
    "content": {
      "type": "richtext"
    },
    "media": {
      "model": "file",
      "via": "related",
      "allowedTypes": [
        "images",
        "files",
        "videos"
      ],
      "plugin": "upload",
      "required": false,
      "pluginOptions": {}
    },
    "url": {
      "type": "string"
    }
  }
}
